{
  "coord": {
    "lon": -2.3591,
    "lat": 51.3779
  },
  "weather": [
    {
      "id": 804,
      "main": "Clouds",
      "description": "overcast clouds",
      "icon": "04d"
    }
  ],
  "base": "stations",
  "main": {
    "temp": 8.39,
    "feels_like": 5.99,
    "temp_min": 8.39,
    "temp_max": 8.39,
    "pressure": 1022,
    "humidity": 94,
    "sea_level": 1022,
    "grnd_level": 1008
  },
  "visibility": 10000,
  "wind": {
    "speed": 4.07,
    "deg": 269,
    "gust": 7.57
  },
  "clouds": {
    "all": 95
  },
  "dt": 1776496335,
  "sys": {
    "country": "GB",
    "sunrise": 1776488864,
    "sunset": 1776539368
  },
  "timezone": 3600,
  "id": 2656173,
  "name": "Bath",
  "cod": 200,
  "_last_updated_utc": "2026-04-18T07:12:16.020Z"
}