{
  "coord": {
    "lon": -2.3591,
    "lat": 51.3779
  },
  "weather": [
    {
      "id": 803,
      "main": "Clouds",
      "description": "broken clouds",
      "icon": "04d"
    }
  ],
  "base": "stations",
  "main": {
    "temp": 14.16,
    "feels_like": 12.99,
    "temp_min": 14.16,
    "temp_max": 14.16,
    "pressure": 1023,
    "humidity": 52,
    "sea_level": 1023,
    "grnd_level": 1009
  },
  "visibility": 10000,
  "wind": {
    "speed": 4.85,
    "deg": 78,
    "gust": 5.17
  },
  "clouds": {
    "all": 63
  },
  "dt": 1776692863,
  "sys": {
    "country": "GB",
    "sunrise": 1776661414,
    "sunset": 1776712368
  },
  "timezone": 3600,
  "id": 2656173,
  "name": "Bath",
  "cod": 200,
  "_last_updated_utc": "2026-04-20T13:47:43.630Z"
}