{
  "coord": {
    "lon": -2.3591,
    "lat": 51.3779
  },
  "weather": [
    {
      "id": 804,
      "main": "Clouds",
      "description": "overcast clouds",
      "icon": "04n"
    }
  ],
  "base": "stations",
  "main": {
    "temp": 11.33,
    "feels_like": 10.76,
    "temp_min": 11.02,
    "temp_max": 12.02,
    "pressure": 1005,
    "humidity": 86,
    "sea_level": 1005,
    "grnd_level": 991
  },
  "visibility": 10000,
  "wind": {
    "speed": 12.28,
    "deg": 215,
    "gust": 24.47
  },
  "clouds": {
    "all": 100
  },
  "dt": 1775334887,
  "sys": {
    "type": 2,
    "id": 2081691,
    "country": "GB",
    "sunrise": 1775281101,
    "sunset": 1775328373
  },
  "timezone": 3600,
  "id": 2656173,
  "name": "Bath",
  "cod": 200,
  "_last_updated_utc": "2026-04-04T20:35:37.671Z"
}