{
  "coord": {
    "lon": -2.3591,
    "lat": 51.3779
  },
  "weather": [
    {
      "id": 803,
      "main": "Clouds",
      "description": "broken clouds",
      "icon": "04d"
    }
  ],
  "base": "stations",
  "main": {
    "temp": 24.87,
    "feels_like": 24.43,
    "temp_min": 23.94,
    "temp_max": 25.77,
    "pressure": 1023,
    "humidity": 39,
    "sea_level": 1023,
    "grnd_level": 1009
  },
  "visibility": 10000,
  "wind": {
    "speed": 4.58,
    "deg": 333,
    "gust": 5.76
  },
  "clouds": {
    "all": 81
  },
  "dt": 1784480364,
  "sys": {
    "type": 2,
    "id": 2081691,
    "country": "GB",
    "sunrise": 1784434503,
    "sunset": 1784492160
  },
  "timezone": 3600,
  "id": 2656173,
  "name": "Bath",
  "cod": 200,
  "_last_updated_utc": "2026-07-19T16:59:24.699Z"
}